xsbe/__init__.py
xsbe/transform.py
xsbe-2.1.dist-info/LICENCE.md
xsbe-2.1.dist-info/METADATA
xsbe-2.1.dist-info/WHEEL
xsbe-2.1.dist-info/top_level.txt
xsbe-2.1.dist-info/zip-safe
xsbe-2.1.dist-info/RECORD
