Metadata-Version: 2.1
Name: xsbe
Version: 2.1
Summary: Tool for parsing XML using example XML documents as a schema
Home-page: https://github.com/couling/XSBE
Author: Philip Couling
Author-email: couling@gmail.com
License: MIT
Platform: any
Classifier: License :: OSI Approved :: MIT License
Classifier: Programming Language :: Python :: 3
Classifier: Programming Language :: Python :: 3.8
License-File: LICENCE.md
Provides-Extra: tests
Requires-Dist: pytest ; extra == 'tests'
